static_frame_pyodide/__init__.py
static_frame_pyodide-1.4.5.dist-info/LICENSE
static_frame_pyodide-1.4.5.dist-info/METADATA
static_frame_pyodide-1.4.5.dist-info/WHEEL
static_frame_pyodide-1.4.5.dist-info/top_level.txt
static_frame_pyodide-1.4.5.dist-info/RECORD
